fastpwa-0.3.1b0.dist-info/METADATA
fastpwa-0.3.1b0.dist-info/WHEEL
fastpwa-0.3.1b0.dist-info/entry_points.txt
fastpwa/__init__.py
fastpwa-0.3.1b0.dist-info/RECORD
