Metadata-Version: 2.1
Name: FastPWA
Version: 0.3.1b0
Summary: Make your FastAPI app installable on mobile devices.
Keywords: pwa,progressive,web,app,windows,android,iphone,apple,ios,safari
Author-Email: Cody M Sommer <bassmastacod@gmail.com>
License: MIT
Classifier: License :: OSI Approved :: MIT License
Classifier: Programming Language :: Python :: 3.7
Classifier: Programming Language :: Python :: 3.8
Classifier: Programming Language :: Python :: 3.9
Classifier: Programming Language :: Python :: 3.10
Classifier: Programming Language :: Python :: 3.11
Classifier: Programming Language :: Python :: 3.12
Classifier: Programming Language :: Python :: 3.13
Classifier: Programming Language :: Python :: 3.14
Classifier: Development Status :: 2 - Pre-Alpha
Classifier: Intended Audience :: Developers
Classifier: Topic :: Software Development :: Libraries
Classifier: Typing :: Typed
Project-URL: Repository, https://github.com/BassMastaCod/FastPWA.git
Project-URL: Issues, https://github.com/BassMastaCod/FastPWA/issues
Requires-Python: >=3.7
Requires-Dist: fastapi
Requires-Dist: pydantic
Requires-Dist: jinja2
